packinfo_cli/__init__.py
packinfo_cli/entrypoint.py
packinfo_cli-0.1.0.dist-info/entry_points.txt
packinfo_cli-0.1.0.dist-info/WHEEL
packinfo_cli-0.1.0.dist-info/METADATA
packinfo_cli-0.1.0.dist-info/RECORD
