Metadata-Version: 2.1
Name: packinfo-cli
Version: 0.1.0
Summary: 
Author: Guillaume Gauvrit
Author-email: guillaume@gauvr.it
Requires-Python: >=3.10,<4.0
Classifier: Programming Language :: Python :: 3
Classifier: Programming Language :: Python :: 3.10
Classifier: Programming Language :: Python :: 3.11
Requires-Dist: click (>=8.1.3,<9.0.0)
Requires-Dist: requests (>=2.28.1,<3.0.0)
